.gitignore
MANIFEST.in
README.rst
setup.cfg
setup.py
docs/HISTORY.txt
raptus/__init__.py
raptus.carousel.egg-info/PKG-INFO
raptus.carousel.egg-info/SOURCES.txt
raptus.carousel.egg-info/dependency_links.txt
raptus.carousel.egg-info/entry_points.txt
raptus.carousel.egg-info/namespace_packages.txt
raptus.carousel.egg-info/not-zip-safe
raptus.carousel.egg-info/requires.txt
raptus.carousel.egg-info/top_level.txt
raptus/carousel/__init__.py
raptus/carousel/configure.zcml
raptus/carousel/browser/__init__.py
raptus/carousel/browser/carousel.init.js
raptus/carousel/browser/carousel.js
raptus/carousel/browser/configure.zcml
raptus/carousel/browser/next.gif
raptus/carousel/browser/prev.gif
raptus/carousel/profiles/default/cssregistry.xml
raptus/carousel/profiles/default/jsregistry.xml
raptus/carousel/profiles/default/metadata.xml
raptus/carousel/profiles/default/propertiestool.xml
raptus/carousel/profiles/default/skins.xml
raptus/carousel/skins/raptus_carousel/carousel.settings.js.py
raptus/carousel/skins/raptus_carousel/raptus.carousel.css.dtml