Metadata-Version: 1.0
Name: raptus.carousel
Version: 2.0b5
Summary: Provides a jquery plugin to display a carousel
Home-page: https://github.com/Raptus/raptus.carousel
Author: Raptus AG
Author-email: dev@raptus.com
License: GPL
Platform: UNKNOWN
Classifier: Programming Language :: Python
Classifier: Topic :: Software Development :: Libraries :: Python Modules
